Metadata-Version: 2.1
Name: gamfra-test-probability
Version: 0.1
Summary: Gaussian and Binomial distributions
Home-page: UNKNOWN
Author: Francis Gambini
Author-email: francisgambini@outlook.com
License: UNKNOWN
Platform: UNKNOWN
